madeira/__init__.py
madeira/acm.py
madeira/athena.py
madeira/aws_lambda.py
madeira/cloudformation.py
madeira/cloudfront.py
madeira/cloudwatch.py
madeira/ec2.py
madeira/ecr.py
madeira/ecs.py
madeira/elbv2.py
madeira/glue.py
madeira/iam.py
madeira/kms.py
madeira/logs.py
madeira/quicksight.py
madeira/rds.py
madeira/redshift.py
madeira/route_53.py
madeira/s3.py
madeira/secrets_manager.py
madeira/session.py
madeira/sqs.py
madeira/step_functions.py
madeira/sts.py
madeira/vpc.py
madeira-1.0.24.dist-info/METADATA
madeira-1.0.24.dist-info/WHEEL
madeira-1.0.24.dist-info/top_level.txt
madeira-1.0.24.dist-info/RECORD
