Metadata-Version: 2.1
Name: madeira
Version: 1.0.24
Summary: Common AWS operation wrappers
Home-page: https://github.com/mxmader/madeira
Author: Joe Mader
Author-email: jmader@jmader.com
License: MIT
Platform: UNKNOWN
Classifier: License :: OSI Approved :: MIT License
Classifier: Programming Language :: Python :: 3
Classifier: Programming Language :: Python :: 3.7
Classifier: Programming Language :: Python :: 3.8
Requires-Dist: boto3
Requires-Dist: madeira-utils
